gtirb/__init__.py
gtirb/auxdata.py
gtirb/block.py
gtirb/byteinterval.py
gtirb/cfg.py
gtirb/ir.py
gtirb/lazyintervaltree.py
gtirb/module.py
gtirb/node.py
gtirb/offset.py
gtirb/py.typed
gtirb/section.py
gtirb/serialization.py
gtirb/symbol.py
gtirb/symbolicexpression.py
gtirb/util.py
gtirb/version.py
gtirb/proto/AuxData_pb2.py
gtirb/proto/AuxData_pb2.pyi
gtirb/proto/ByteInterval_pb2.py
gtirb/proto/ByteInterval_pb2.pyi
gtirb/proto/CFG_pb2.py
gtirb/proto/CFG_pb2.pyi
gtirb/proto/CodeBlock_pb2.py
gtirb/proto/CodeBlock_pb2.pyi
gtirb/proto/DataBlock_pb2.py
gtirb/proto/DataBlock_pb2.pyi
gtirb/proto/IR_pb2.py
gtirb/proto/IR_pb2.pyi
gtirb/proto/Module_pb2.py
gtirb/proto/Module_pb2.pyi
gtirb/proto/Offset_pb2.py
gtirb/proto/Offset_pb2.pyi
gtirb/proto/ProxyBlock_pb2.py
gtirb/proto/ProxyBlock_pb2.pyi
gtirb/proto/Section_pb2.py
gtirb/proto/Section_pb2.pyi
gtirb/proto/Symbol_pb2.py
gtirb/proto/Symbol_pb2.pyi
gtirb/proto/SymbolicExpression_pb2.py
gtirb/proto/SymbolicExpression_pb2.pyi
gtirb/proto/__init__.py
gtirb-2.3.0.dist-info/licenses/LICENSE
gtirb-2.3.0.dist-info/METADATA
gtirb-2.3.0.dist-info/WHEEL
gtirb-2.3.0.dist-info/top_level.txt
gtirb-2.3.0.dist-info/RECORD
