Metadata-Version: 2.4
Name: gtirb
Version: 2.3.0
Summary: GrammaTech Intermediate Representation for Binaries
Home-page: https://github.com/grammatech/gtirb
Author: GrammaTech
Author-email: gtirb@grammatech.com
License: MIT
Classifier: Programming Language :: Python :: 3
Classifier: License :: OSI Approved :: MIT License
Classifier: Operating System :: OS Independent
Requires-Python: >=3.6
License-File: LICENSE
Requires-Dist: networkx
Requires-Dist: protobuf>=4.0
Requires-Dist: intervaltree
Requires-Dist: sortedcontainers
Requires-Dist: typing-extensions>=3.7.4.2
Provides-Extra: doc
Requires-Dist: sphinx; extra == "doc"
Requires-Dist: sphinx-autodoc-typehints; extra == "doc"
Dynamic: author
Dynamic: author-email
Dynamic: classifier
Dynamic: description
Dynamic: description-content-type
Dynamic: home-page
Dynamic: license
Dynamic: license-file
Dynamic: provides-extra
Dynamic: requires-dist
Dynamic: requires-python
Dynamic: summary
